<?xml version="1.0" encoding="UTF-8"?>
<con:soapui-project id="333a3dcb-38e4-49ec-8b6a-f5355d449027" created="3.47.0" activeEnvironment="Default environment" encryptionMode="Not encrypted" name="CalculatorSoapC" projectVersion="" updated="3.47.0 2023-06-30T11:24:47Z" xmlns:con="http://eviware.com/soapui/config">
  <con:settings/>
  <con:interface xsi:type="con:WsdlInterface" id="e3ef4ad3-1c06-4ee0-9912-bb106e8f60fb" wsaVersion="NONE" name="CalculatorSoap" type="wsdl" bindingName="{http://tempuri.org/}CalculatorSoap" soapVersion="1_1" anonymous="optional" definition="http://www.dneonline.com/calculator.asmx?WSDL" xmlns:xsi="http://www.w3.org/2001/XMLSchema-instance">
    <con:settings id="fecc4d2a-1390-4e67-b7e4-3ade8c6a62e7"/>
    <con:definitionCache type="TEXT" rootPart="http://www.dneonline.com/calculator.asmx?WSDL">
      <con:part>
        <con:url>http://www.dneonline.com/calculator.asmx?WSDL</con:url>
        <con:content><![CDATA[<wsdl:definitions targetNamespace="http://tempuri.org/" xmlns:soap="http://schemas.xmlsoap.org/wsdl/soap/" xmlns:tm="http://microsoft.com/wsdl/mime/textMatching/" xmlns:soapenc="http://schemas.xmlsoap.org/soap/encoding/" xmlns:mime="http://schemas.xmlsoap.org/wsdl/mime/" xmlns:tns="http://tempuri.org/" xmlns:s="http://www.w3.org/2001/XMLSchema" xmlns:soap12="http://schemas.xmlsoap.org/wsdl/soap12/" xmlns:http="http://schemas.xmlsoap.org/wsdl/http/" xmlns:wsdl="http://schemas.xmlsoap.org/wsdl/">
  <wsdl:types>
    <s:schema elementFormDefault="qualified" targetNamespace="http://tempuri.org/">
      <s:element name="Add">
        <s:complexType>
          <s:sequence>
            <s:element minOccurs="1" maxOccurs="1" name="intA" type="s:int"/>
            <s:element minOccurs="1" maxOccurs="1" name="intB" type="s:int"/>
          </s:sequence>
        </s:complexType>
      </s:element>
      <s:element name="AddResponse">
        <s:complexType>
          <s:sequence>
            <s:element minOccurs="1" maxOccurs="1" name="AddResult" type="s:int"/>
          </s:sequence>
        </s:complexType>
      </s:element>
      <s:element name="Subtract">
        <s:complexType>
          <s:sequence>
            <s:element minOccurs="1" maxOccurs="1" name="intA" type="s:int"/>
            <s:element minOccurs="1" maxOccurs="1" name="intB" type="s:int"/>
          </s:sequence>
        </s:complexType>
      </s:element>
      <s:element name="SubtractResponse">
        <s:complexType>
          <s:sequence>
            <s:element minOccurs="1" maxOccurs="1" name="SubtractResult" type="s:int"/>
          </s:sequence>
        </s:complexType>
      </s:element>
      <s:element name="Multiply">
        <s:complexType>
          <s:sequence>
            <s:element minOccurs="1" maxOccurs="1" name="intA" type="s:int"/>
            <s:element minOccurs="1" maxOccurs="1" name="intB" type="s:int"/>
          </s:sequence>
        </s:complexType>
      </s:element>
      <s:element name="MultiplyResponse">
        <s:complexType>
          <s:sequence>
            <s:element minOccurs="1" maxOccurs="1" name="MultiplyResult" type="s:int"/>
          </s:sequence>
        </s:complexType>
      </s:element>
      <s:element name="Divide">
        <s:complexType>
          <s:sequence>
            <s:element minOccurs="1" maxOccurs="1" name="intA" type="s:int"/>
            <s:element minOccurs="1" maxOccurs="1" name="intB" type="s:int"/>
          </s:sequence>
        </s:complexType>
      </s:element>
      <s:element name="DivideResponse">
        <s:complexType>
          <s:sequence>
            <s:element minOccurs="1" maxOccurs="1" name="DivideResult" type="s:int"/>
          </s:sequence>
        </s:complexType>
      </s:element>
    </s:schema>
  </wsdl:types>
  <wsdl:message name="AddSoapIn">
    <wsdl:part name="parameters" element="tns:Add"/>
  </wsdl:message>
  <wsdl:message name="AddSoapOut">
    <wsdl:part name="parameters" element="tns:AddResponse"/>
  </wsdl:message>
  <wsdl:message name="SubtractSoapIn">
    <wsdl:part name="parameters" element="tns:Subtract"/>
  </wsdl:message>
  <wsdl:message name="SubtractSoapOut">
    <wsdl:part name="parameters" element="tns:SubtractResponse"/>
  </wsdl:message>
  <wsdl:message name="MultiplySoapIn">
    <wsdl:part name="parameters" element="tns:Multiply"/>
  </wsdl:message>
  <wsdl:message name="MultiplySoapOut">
    <wsdl:part name="parameters" element="tns:MultiplyResponse"/>
  </wsdl:message>
  <wsdl:message name="DivideSoapIn">
    <wsdl:part name="parameters" element="tns:Divide"/>
  </wsdl:message>
  <wsdl:message name="DivideSoapOut">
    <wsdl:part name="parameters" element="tns:DivideResponse"/>
  </wsdl:message>
  <wsdl:portType name="CalculatorSoap">
    <wsdl:operation name="Add">
      <wsdl:documentation>Adds two integers. This is a test WebService. ©DNE Online</wsdl:documentation>
      <wsdl:input message="tns:AddSoapIn"/>
      <wsdl:output message="tns:AddSoapOut"/>
    </wsdl:operation>
    <wsdl:operation name="Subtract">
      <wsdl:input message="tns:SubtractSoapIn"/>
      <wsdl:output message="tns:SubtractSoapOut"/>
    </wsdl:operation>
    <wsdl:operation name="Multiply">
      <wsdl:input message="tns:MultiplySoapIn"/>
      <wsdl:output message="tns:MultiplySoapOut"/>
    </wsdl:operation>
    <wsdl:operation name="Divide">
      <wsdl:input message="tns:DivideSoapIn"/>
      <wsdl:output message="tns:DivideSoapOut"/>
    </wsdl:operation>
  </wsdl:portType>
  <wsdl:binding name="CalculatorSoap" type="tns:CalculatorSoap">
    <soap:binding transport="http://schemas.xmlsoap.org/soap/http"/>
    <wsdl:operation name="Add">
      <soap:operation soapAction="http://tempuri.org/Add" style="document"/>
      <wsdl:input>
        <soap:body use="literal"/>
      </wsdl:input>
      <wsdl:output>
        <soap:body use="literal"/>
      </wsdl:output>
    </wsdl:operation>
    <wsdl:operation name="Subtract">
      <soap:operation soapAction="http://tempuri.org/Subtract" style="document"/>
      <wsdl:input>
        <soap:body use="literal"/>
      </wsdl:input>
      <wsdl:output>
        <soap:body use="literal"/>
      </wsdl:output>
    </wsdl:operation>
    <wsdl:operation name="Multiply">
      <soap:operation soapAction="http://tempuri.org/Multiply" style="document"/>
      <wsdl:input>
        <soap:body use="literal"/>
      </wsdl:input>
      <wsdl:output>
        <soap:body use="literal"/>
      </wsdl:output>
    </wsdl:operation>
    <wsdl:operation name="Divide">
      <soap:operation soapAction="http://tempuri.org/Divide" style="document"/>
      <wsdl:input>
        <soap:body use="literal"/>
      </wsdl:input>
      <wsdl:output>
        <soap:body use="literal"/>
      </wsdl:output>
    </wsdl:operation>
  </wsdl:binding>
  <wsdl:binding name="CalculatorSoap12" type="tns:CalculatorSoap">
    <soap12:binding transport="http://schemas.xmlsoap.org/soap/http"/>
    <wsdl:operation name="Add">
      <soap12:operation soapAction="http://tempuri.org/Add" style="document"/>
      <wsdl:input>
        <soap12:body use="literal"/>
      </wsdl:input>
      <wsdl:output>
        <soap12:body use="literal"/>
      </wsdl:output>
    </wsdl:operation>
    <wsdl:operation name="Subtract">
      <soap12:operation soapAction="http://tempuri.org/Subtract" style="document"/>
      <wsdl:input>
        <soap12:body use="literal"/>
      </wsdl:input>
      <wsdl:output>
        <soap12:body use="literal"/>
      </wsdl:output>
    </wsdl:operation>
    <wsdl:operation name="Multiply">
      <soap12:operation soapAction="http://tempuri.org/Multiply" style="document"/>
      <wsdl:input>
        <soap12:body use="literal"/>
      </wsdl:input>
      <wsdl:output>
        <soap12:body use="literal"/>
      </wsdl:output>
    </wsdl:operation>
    <wsdl:operation name="Divide">
      <soap12:operation soapAction="http://tempuri.org/Divide" style="document"/>
      <wsdl:input>
        <soap12:body use="literal"/>
      </wsdl:input>
      <wsdl:output>
        <soap12:body use="literal"/>
      </wsdl:output>
    </wsdl:operation>
  </wsdl:binding>
  <wsdl:service name="Calculator">
    <wsdl:port name="CalculatorSoap" binding="tns:CalculatorSoap">
      <soap:address location="http://www.dneonline.com/calculator.asmx"/>
    </wsdl:port>
    <wsdl:port name="CalculatorSoap12" binding="tns:CalculatorSoap12">
      <soap12:address location="http://www.dneonline.com/calculator.asmx"/>
    </wsdl:port>
  </wsdl:service>
</wsdl:definitions>]]></con:content>
        <con:type>http://schemas.xmlsoap.org/wsdl/</con:type>
      </con:part>
    </con:definitionCache>
    <con:endpoints>
      <con:endpoint>http://www.dneonline.com/calculator.asmx</con:endpoint>
    </con:endpoints>
    <con:operation id="90020e25-d80f-47b3-bbec-e22edac2983e" isOneWay="false" action="http://tempuri.org/Add" name="Add" bindingOperationName="Add" type="Request-Response" inputName="" receivesAttachments="false" sendsAttachments="false" anonymous="optional">
      <con:settings/>
      <con:call id="46aa806b-5137-4743-87e8-8d4ded24d7f5" name="Add Request">
        <con:settings/>
        <con:encoding>UTF-8</con:encoding>
        <con:endpoint>http://www.dneonline.com/calculator.asmx</con:endpoint>
        <con:request><![CDATA[<soapenv:Envelope xmlns:soapenv="http://schemas.xmlsoap.org/soap/envelope/" xmlns:tem="http://tempuri.org/">
   <soapenv:Header/>
   <soapenv:Body>
      <tem:Add>
         <tem:intA>?</tem:intA>
         <tem:intB>?</tem:intB>
      </tem:Add>
   </soapenv:Body>
</soapenv:Envelope>]]></con:request>
        <con:credentials>
          <con:selectedAuthProfile>No Authorization</con:selectedAuthProfile>
          <con:authType>No Authorization</con:authType>
        </con:credentials>
        <con:wsaConfig mustUnderstand="NONE" version="200508" action="http://tempuri.org/Add"/>
      </con:call>
    </con:operation>
    <con:operation id="97134813-f02b-4d44-9c9e-46a97f0726e7" isOneWay="false" action="http://tempuri.org/Divide" name="Divide" bindingOperationName="Divide" type="Request-Response" inputName="" receivesAttachments="false" sendsAttachments="false" anonymous="optional">
      <con:settings/>
      <con:call id="6092b6d8-f7e8-4d4f-b2f5-f3e99288c2c0" name="Divide Request">
        <con:settings/>
        <con:encoding>UTF-8</con:encoding>
        <con:endpoint>http://www.dneonline.com/calculator.asmx</con:endpoint>
        <con:request><![CDATA[<soapenv:Envelope xmlns:soapenv="http://schemas.xmlsoap.org/soap/envelope/" xmlns:tem="http://tempuri.org/">
   <soapenv:Header/>
   <soapenv:Body>
      <tem:Divide>
         <tem:intA>?</tem:intA>
         <tem:intB>?</tem:intB>
      </tem:Divide>
   </soapenv:Body>
</soapenv:Envelope>]]></con:request>
        <con:credentials>
          <con:selectedAuthProfile>No Authorization</con:selectedAuthProfile>
          <con:authType>No Authorization</con:authType>
        </con:credentials>
        <con:wsaConfig mustUnderstand="NONE" version="200508" action="http://tempuri.org/Divide"/>
      </con:call>
    </con:operation>
    <con:operation id="139c855c-b5ea-4610-bd9a-f1da98946d84" isOneWay="false" action="http://tempuri.org/Multiply" name="Multiply" bindingOperationName="Multiply" type="Request-Response" inputName="" receivesAttachments="false" sendsAttachments="false" anonymous="optional">
      <con:settings/>
      <con:call id="141ca65d-9159-4e69-86f9-be87219d4f06" name="Multiply Request">
        <con:settings/>
        <con:encoding>UTF-8</con:encoding>
        <con:endpoint>http://www.dneonline.com/calculator.asmx</con:endpoint>
        <con:request><![CDATA[<soapenv:Envelope xmlns:soapenv="http://schemas.xmlsoap.org/soap/envelope/" xmlns:tem="http://tempuri.org/">
   <soapenv:Header/>
   <soapenv:Body>
      <tem:Multiply>
         <tem:intA>?</tem:intA>
         <tem:intB>?</tem:intB>
      </tem:Multiply>
   </soapenv:Body>
</soapenv:Envelope>]]></con:request>
        <con:credentials>
          <con:selectedAuthProfile>No Authorization</con:selectedAuthProfile>
          <con:authType>No Authorization</con:authType>
        </con:credentials>
        <con:wsaConfig mustUnderstand="NONE" version="200508" action="http://tempuri.org/Multiply"/>
      </con:call>
    </con:operation>
    <con:operation id="8e471c57-89e5-480e-b62c-8961feb18f0f" isOneWay="false" action="http://tempuri.org/Subtract" name="Subtract" bindingOperationName="Subtract" type="Request-Response" inputName="" receivesAttachments="false" sendsAttachments="false" anonymous="optional">
      <con:settings/>
      <con:call id="cc87e3ae-cd1b-48d5-8661-153d7f124011" name="Subtract Request">
        <con:settings/>
        <con:encoding>UTF-8</con:encoding>
        <con:endpoint>http://www.dneonline.com/calculator.asmx</con:endpoint>
        <con:request><![CDATA[<soapenv:Envelope xmlns:soapenv="http://schemas.xmlsoap.org/soap/envelope/" xmlns:tem="http://tempuri.org/">
   <soapenv:Header/>
   <soapenv:Body>
      <tem:Subtract>
         <tem:intA>?</tem:intA>
         <tem:intB>?</tem:intB>
      </tem:Subtract>
   </soapenv:Body>
</soapenv:Envelope>]]></con:request>
        <con:credentials>
          <con:selectedAuthProfile>No Authorization</con:selectedAuthProfile>
          <con:authType>No Authorization</con:authType>
        </con:credentials>
        <con:wsaConfig mustUnderstand="NONE" version="200508" action="http://tempuri.org/Subtract"/>
      </con:call>
    </con:operation>
  </con:interface>
  <con:testSuite id="a906498a-7e60-4cb3-bd66-8edf8f2d5edb" name="Test Suit">
    <con:settings id="9b96355a-b8a0-42f7-9818-d35d69c2d73c"/>
    <con:runType>SEQUENTIAL</con:runType>
    <con:testCase id="4b520ba8-6a15-40f8-a935-81714995883b" discardOkResults="false" failOnError="false" failTestCaseOnErrors="true" keepSession="false" name="testcase" searchProperties="true" timeout="0">
      <con:settings/>
      <con:testStep type="request" id="ae5decbe-b417-4617-b80e-37213b7e7513" name="AddRequest">
        <con:settings/>
        <con:config xsi:type="con:RequestStep" xmlns:xsi="http://www.w3.org/2001/XMLSchema-instance">
          <con:interface>CalculatorSoap</con:interface>
          <con:operation>Add</con:operation>
          <con:request name="AddRequest" outgoingWss="" incomingWss="" timeout="" sslKeystore="" useWsAddressing="false" useWsReliableMessaging="false" wssPasswordType="" id="26635ed3-369e-4866-85a4-2a9489417c84">
            <con:settings>
              <con:setting id="com.eviware.soapui.impl.wsdl.WsdlRequest@request-headers">&lt;xml-fragment/></con:setting>
            </con:settings>
            <con:encoding>UTF-8</con:encoding>
            <con:endpoint>http://www.dneonline.com/calculator.asmx</con:endpoint>
            <con:request><![CDATA[<soapenv:Envelope xmlns:soapenv="http://schemas.xmlsoap.org/soap/envelope/" xmlns:tem="http://tempuri.org/">
   <soapenv:Header/>
   <soapenv:Body>
      <tem:Add>
         <tem:intA>20</tem:intA>
         <tem:intB>10</tem:intB>
      </tem:Add>
   </soapenv:Body>
</soapenv:Envelope>]]></con:request>
            <con:assertion type="SOAP Response" id="87ce50ce-8a90-41ec-87cc-d440130b26b9" name="SOAP Response"/>
            <con:assertion type="Valid HTTP Status Codes" id="4371840b-a806-428e-b1af-c80dd6a98876" name="Valid HTTP Status Codes">
              <con:settings/>
              <con:configuration>
                <codes>200</codes>
              </con:configuration>
            </con:assertion>
            <con:assertion type="Schema Compliance" id="3c9117d3-3f69-47ee-883b-3ad267cad197" name="Schema Compliance">
              <con:configuration/>
            </con:assertion>
            <con:assertion type="SOAP Fault Assertion" id="79d21918-68d1-4f7e-a2c8-0d3a670cafed" name="Not SOAP Fault"/>
            <con:assertion type="XPath Match" id="361f1bfc-9106-494a-a76d-4d89e484c8c3" name="XPath Match">
              <con:configuration>
                <path>declare namespace ns1='http://tempuri.org/';
//ns1:AddResponse[1]/ns1:AddResult[1]</path>
                <content>30</content>
                <allowWildcards>false</allowWildcards>
                <ignoreNamspaceDifferences>false</ignoreNamspaceDifferences>
                <ignoreComments>false</ignoreComments>
              </con:configuration>
            </con:assertion>
            <con:credentials>
              <con:selectedAuthProfile>No Authorization</con:selectedAuthProfile>
              <con:authType>No Authorization</con:authType>
            </con:credentials>
            <con:jmsConfig JMSDeliveryMode="PERSISTENT"/>
            <con:wsaConfig mustUnderstand="NONE" version="200508" action="http://tempuri.org/Add"/>
            <con:wsrmConfig version="1.2"/>
          </con:request>
        </con:config>
      </con:testStep>
      <con:testStep type="request" id="aab14f15-00f8-4594-b867-259a6ba4dca0" name="DivideRequest">
        <con:settings/>
        <con:config xsi:type="con:RequestStep" xmlns:xsi="http://www.w3.org/2001/XMLSchema-instance">
          <con:interface>CalculatorSoap</con:interface>
          <con:operation>Divide</con:operation>
          <con:request name="DivideRequest" outgoingWss="" incomingWss="" timeout="" sslKeystore="" useWsAddressing="false" useWsReliableMessaging="false" wssPasswordType="" id="26f5a6ef-3d32-42ed-8fe4-4dc6a3a22445">
            <con:settings>
              <con:setting id="com.eviware.soapui.impl.wsdl.WsdlRequest@request-headers">&lt;xml-fragment/></con:setting>
            </con:settings>
            <con:encoding>UTF-8</con:encoding>
            <con:endpoint>http://www.dneonline.com/calculator.asmx</con:endpoint>
            <con:request><![CDATA[<soapenv:Envelope xmlns:soapenv="http://schemas.xmlsoap.org/soap/envelope/" xmlns:tem="http://tempuri.org/">
   <soapenv:Header/>
   <soapenv:Body>
      <tem:Divide>
         <tem:intA>56</tem:intA>
         <tem:intB>34</tem:intB>
      </tem:Divide>
   </soapenv:Body>
</soapenv:Envelope>]]></con:request>
            <con:assertion type="SOAP Response" id="053b25b5-6c57-4ab5-92bc-a064b0da5fc5" name="SOAP Response"/>
            <con:assertion type="Valid HTTP Status Codes" id="601c0033-8925-43ec-816a-b25e49000242" name="Valid HTTP Status Codes">
              <con:settings/>
              <con:configuration>
                <codes>200</codes>
              </con:configuration>
            </con:assertion>
            <con:assertion type="Schema Compliance" id="2b2705dd-e8ad-408f-95f7-bc71a69d9c30" name="Schema Compliance">
              <con:configuration/>
            </con:assertion>
            <con:assertion type="SOAP Fault Assertion" id="6ddf744f-9968-4a3b-89f4-596b55ae623c" name="Not SOAP Fault"/>
            <con:credentials>
              <con:selectedAuthProfile>No Authorization</con:selectedAuthProfile>
              <con:authType>No Authorization</con:authType>
            </con:credentials>
            <con:jmsConfig JMSDeliveryMode="PERSISTENT"/>
            <con:wsaConfig mustUnderstand="NONE" version="200508" action="http://tempuri.org/Divide"/>
            <con:wsrmConfig version="1.2"/>
          </con:request>
        </con:config>
      </con:testStep>
      <con:testStep type="request" id="ff954bcd-9908-4cef-ac09-4835ea7de5b7" name="MultiplyRequest">
        <con:settings/>
        <con:config xsi:type="con:RequestStep" xmlns:xsi="http://www.w3.org/2001/XMLSchema-instance">
          <con:interface>CalculatorSoap</con:interface>
          <con:operation>Multiply</con:operation>
          <con:request name="MultiplyRequest" outgoingWss="" incomingWss="" timeout="" sslKeystore="" useWsAddressing="false" useWsReliableMessaging="false" wssPasswordType="" id="fa430ba1-ff93-489e-bbcc-15a578cb08bc">
            <con:settings>
              <con:setting id="com.eviware.soapui.impl.wsdl.WsdlRequest@request-headers">&lt;xml-fragment/></con:setting>
            </con:settings>
            <con:encoding>UTF-8</con:encoding>
            <con:endpoint>http://www.dneonline.com/calculator.asmx</con:endpoint>
            <con:request><![CDATA[<soapenv:Envelope xmlns:soapenv="http://schemas.xmlsoap.org/soap/envelope/" xmlns:tem="http://tempuri.org/">
   <soapenv:Header/>
   <soapenv:Body>
      <tem:Multiply>
         <tem:intA>23</tem:intA>
         <tem:intB>3</tem:intB>
      </tem:Multiply>
   </soapenv:Body>
</soapenv:Envelope>]]></con:request>
            <con:assertion type="SOAP Response" id="c02eaa78-ba50-450e-aaa5-2ca65325d773" name="SOAP Response"/>
            <con:assertion type="Valid HTTP Status Codes" id="537204c9-b745-40c6-ae9d-2dbd84e293b6" name="Valid HTTP Status Codes">
              <con:settings/>
              <con:configuration>
                <codes>200</codes>
              </con:configuration>
            </con:assertion>
            <con:assertion type="Schema Compliance" id="9b71a494-2ea5-47e5-992a-f8fd3bb2362e" name="Schema Compliance">
              <con:configuration/>
            </con:assertion>
            <con:assertion type="SOAP Fault Assertion" id="6704e641-cb5d-404b-a6ec-5594bcba310f" name="Not SOAP Fault"/>
            <con:credentials>
              <con:selectedAuthProfile>No Authorization</con:selectedAuthProfile>
              <con:authType>No Authorization</con:authType>
            </con:credentials>
            <con:jmsConfig JMSDeliveryMode="PERSISTENT"/>
            <con:wsaConfig mustUnderstand="NONE" version="200508" action="http://tempuri.org/Multiply"/>
            <con:wsrmConfig version="1.2"/>
          </con:request>
        </con:config>
      </con:testStep>
      <con:testStep type="request" id="1ee61b93-22b5-4d5e-9d0d-96fd7427900e" name="SubtractRequest">
        <con:settings/>
        <con:config xsi:type="con:RequestStep" xmlns:xsi="http://www.w3.org/2001/XMLSchema-instance">
          <con:interface>CalculatorSoap</con:interface>
          <con:operation>Subtract</con:operation>
          <con:request name="SubtractRequest" outgoingWss="" incomingWss="" timeout="" sslKeystore="" useWsAddressing="false" useWsReliableMessaging="false" wssPasswordType="" id="c0e4112d-656e-4040-8e6e-e063fac6993b">
            <con:settings>
              <con:setting id="com.eviware.soapui.impl.wsdl.WsdlRequest@request-headers">&lt;xml-fragment/></con:setting>
            </con:settings>
            <con:encoding>UTF-8</con:encoding>
            <con:endpoint>http://www.dneonline.com/calculator.asmx</con:endpoint>
            <con:request><![CDATA[<soapenv:Envelope xmlns:soapenv="http://schemas.xmlsoap.org/soap/envelope/" xmlns:tem="http://tempuri.org/">
   <soapenv:Header/>
   <soapenv:Body>
      <tem:Subtract>
         <tem:intA>45</tem:intA>
         <tem:intB>23</tem:intB>
      </tem:Subtract>
   </soapenv:Body>
</soapenv:Envelope>]]></con:request>
            <con:assertion type="SOAP Response" id="1af136ae-7ec8-4a8c-b912-895d1f8c4452" name="SOAP Response"/>
            <con:assertion type="Valid HTTP Status Codes" id="2bb3ab50-4210-453a-8eaa-d1e103d77bd2" name="Valid HTTP Status Codes">
              <con:settings/>
              <con:configuration>
                <codes>200</codes>
              </con:configuration>
            </con:assertion>
            <con:assertion type="Schema Compliance" id="14a03469-3884-49a2-b55e-f6253b145883" name="Schema Compliance">
              <con:configuration/>
            </con:assertion>
            <con:assertion type="SOAP Fault Assertion" id="247b017e-fd8f-47cb-9b73-ab5cb9da8962" name="Not SOAP Fault"/>
            <con:credentials>
              <con:selectedAuthProfile>No Authorization</con:selectedAuthProfile>
              <con:authType>No Authorization</con:authType>
            </con:credentials>
            <con:jmsConfig JMSDeliveryMode="PERSISTENT"/>
            <con:wsaConfig mustUnderstand="NONE" version="200508" action="http://tempuri.org/Subtract"/>
            <con:wsrmConfig version="1.2"/>
          </con:request>
        </con:config>
      </con:testStep>
      <con:properties/>
      <con:reportParameters/>
    </con:testCase>
    <con:properties/>
    <con:reportParameters/>
  </con:testSuite>
  <con:properties/>
  <con:wssContainer/>
  <con:databaseConnectionContainer/>
  <con:jmsConnectionContainer/>
  <con:oAuth2ProfileContainer/>
  <con:oAuth1ProfileContainer/>
  <con:reporting>
    <con:xmlTemplates/>
    <con:parameters/>
  </con:reporting>
  <con:eventHandlers type="RequestFilter.filterRequest" name="RequestFilter.filterRequest">
    <con:script>// Sample event script to add custom HTTP header to all outgoing REST, SOAP and HTTP(S) calls
// This code is often used for adding custom authentication to ReadyAPI functional tests

// If hardcoding the token, uncomment and change line 5
// token = '4567'

// If your token is parameterized in Project level custom property, uncomment line 8
// token = request.parent.testCase.testSuite.project.getProperty('auth_token').getValue()

// To modify all outgoing calls, remove comments from lines 11 to 16
// headers = request.requestHeaders
// if (headers.containsKey('auth_token2') == false) {
//   headers.put('auth_token2', token)
//   request.requestHeaders = headers
// }</con:script>
  </con:eventHandlers>
  <con:eventHandlers type="TestRunListener.afterStep" name="TestRunListener.afterStep">
    <con:script>// Save all test step results into files
// Change the directory path in line 5 to a location where you want to store details
// then uncomment lines 5 to 10

// filePath = 'C:\\tempOutputDirectory\\'
// fos = new java.io.FileOutputStream(filePath + testStepResult.testStep.label + '.txt', true)
// pw = new java.io.PrintWriter(fos)
// testStepResult.writeTo(pw)
// pw.close()
// fos.close()</con:script>
  </con:eventHandlers>
  <con:authRepository/>
  <con:tags/>
</con:soapui-project>
